fieldrouter-1.0.4.dist-info/METADATA
fieldrouter-1.0.4.dist-info/WHEEL
fieldrouter-1.0.4.dist-info/licenses/LICENSE
fieldrouter/__init__.py
fieldrouter/generic.py
fieldrouter/main.py
fieldrouter-1.0.4.dist-info/RECORD
