Metadata-Version: 2.1
Name: fieldrouter
Version: 1.0.4
Summary: Data model validation for nested data routes
Author-Email: Louis Maddox <louismmx@gmail.com>
License: MIT
Project-URL: Homepage, https://github.com/lmmx/fieldrouter
Project-URL: Repository, https://github.com/lmmx/fieldrouter.git
Requires-Python: >=3.10
Requires-Dist: pydantic>=2.8.2
